supybot/__init__.py
supybot/ansi.py
supybot/callbacks.py
supybot/cdb.py
supybot/commands.py
supybot/conf.py
supybot/dbi.py
supybot/dynamicScope.py
supybot/ircdb.py
supybot/irclib.py
supybot/ircmsgs.py
supybot/ircutils.py
supybot/log.py
supybot/plugin.py
supybot/questions.py
supybot/registry.py
supybot/schedule.py
supybot/shlex.py
supybot/test.py
supybot/unpreserve.py
supybot/version.py
supybot/world.py
supybot/drivers/Socket.py
supybot/drivers/Twisted.py
supybot/drivers/__init__.py
supybot/plugins/__init__.py
supybot/plugins/Admin/__init__.py
supybot/plugins/Admin/config.py
supybot/plugins/Admin/plugin.py
supybot/plugins/Admin/test.py
supybot/plugins/Alias/__init__.py
supybot/plugins/Alias/config.py
supybot/plugins/Alias/plugin.py
supybot/plugins/Alias/test.py
supybot/plugins/Anonymous/__init__.py
supybot/plugins/Anonymous/config.py
supybot/plugins/Anonymous/plugin.py
supybot/plugins/Anonymous/test.py
supybot/plugins/AutoMode/__init__.py
supybot/plugins/AutoMode/config.py
supybot/plugins/AutoMode/plugin.py
supybot/plugins/AutoMode/test.py
supybot/plugins/BadWords/__init__.py
supybot/plugins/BadWords/config.py
supybot/plugins/BadWords/plugin.py
supybot/plugins/BadWords/test.py
supybot/plugins/Channel/__init__.py
supybot/plugins/Channel/config.py
supybot/plugins/Channel/plugin.py
supybot/plugins/Channel/test.py
supybot/plugins/ChannelLogger/__init__.py
supybot/plugins/ChannelLogger/config.py
supybot/plugins/ChannelLogger/plugin.py
supybot/plugins/ChannelLogger/test.py
supybot/plugins/ChannelStats/__init__.py
supybot/plugins/ChannelStats/config.py
supybot/plugins/ChannelStats/plugin.py
supybot/plugins/ChannelStats/test.py
supybot/plugins/Config/__init__.py
supybot/plugins/Config/config.py
supybot/plugins/Config/plugin.py
supybot/plugins/Config/test.py
supybot/plugins/Ctcp/__init__.py
supybot/plugins/Ctcp/config.py
supybot/plugins/Ctcp/plugin.py
supybot/plugins/Ctcp/test.py
supybot-0.84.0.dist-info/DESCRIPTION.rst
supybot-0.84.0.dist-info/METADATA
supybot-0.84.0.dist-info/RECORD
supybot-0.84.0.dist-info/WHEEL
supybot-0.84.0.dist-info/metadata.json
supybot-0.84.0.dist-info/top_level.txt
